napalm_ftos/__init__.py
napalm_ftos/ftos.py
napalm_ftos/utils/__init__.py
napalm_ftos/utils/textfsm_templates/show_arp.tpl
napalm_ftos/utils/textfsm_templates/show_environment_stack-unit.tpl
napalm_ftos/utils/textfsm_templates/show_interfaces.tpl
napalm_ftos/utils/textfsm_templates/show_ip_bgp_neighbors.tpl
napalm_ftos/utils/textfsm_templates/show_lldp_neighbors_detail.tpl
napalm_ftos/utils/textfsm_templates/show_mac-address-table.tpl
napalm_ftos/utils/textfsm_templates/show_memory.tpl
napalm_ftos/utils/textfsm_templates/show_ntp_associations.tpl
napalm_ftos/utils/textfsm_templates/show_processes_cpu_summary.tpl
napalm_ftos/utils/textfsm_templates/traceroute.tpl
napalm_ftos-0.1.2.dist-info/AUTHORS
napalm_ftos-0.1.2.dist-info/LICENSE
napalm_ftos-0.1.2.dist-info/METADATA
napalm_ftos-0.1.2.dist-info/WHEEL
napalm_ftos-0.1.2.dist-info/top_level.txt
napalm_ftos-0.1.2.dist-info/RECORD
