Metadata-Version: 2.1
Name: napalm-ftos
Version: 0.1.2
Summary: NAPALM driver for Force10 FTOS
Home-page: https://github.com/napalm-automation-community/napalm-ftos
Author: Reinier Schoof
Author-email: reinier@skoef.nl
License: UNKNOWN
Platform: UNKNOWN
Classifier: Topic :: Utilities
Classifier: Programming Language :: Python
Classifier: Programming Language :: Python :: 2
Classifier: Programming Language :: Python :: 2.7
Classifier: Programming Language :: Python :: 3
Classifier: Programming Language :: Python :: 3.7
Classifier: Operating System :: POSIX :: Linux
Classifier: Operating System :: Microsoft :: Windows
Classifier: Operating System :: MacOS
Requires-Dist: napalm (>=2.0.0)
